Metadata-Version: 2.1
Name: whatip
Version: 0.0.4
Summary: Console script to find your external IP address
Home-page: https://github.com/lorien/whatip
Author: Gregory Petukhov
Author-email: lorien@lorien.name
Maintainer: Gregory Petukhov
Maintainer-email: lorien@lorien.name
License: MIT License
Download-URL: http://pypi.python.org/pypi/whatip
Keywords: ip internet
Platform: UNKNOWN
Classifier: Programming Language :: Python
Classifier: Programming Language :: Python :: 3.5
Classifier: Programming Language :: Python :: 3.6
Classifier: Programming Language :: Python :: Implementation :: CPython
Classifier: License :: OSI Approved :: MIT License
Classifier: Development Status :: 5 - Production/Stable
Classifier: Operating System :: OS Independent
